[{"name":"Bertrand Shao","img":"https://avatars3.githubusercontent.com/u/56850837?s=400&v=4"},{"name":"Brandon Gomez","img":"https://avatars2.githubusercontent.com/u/59710314?s=400&v=4"},{"name":"Brian Vargas","img":"https://avatars3.githubusercontent.com/u/57280199?s=400&v=4"},{"name":"Bryan Evangelista","img":"https://avatars1.githubusercontent.com/u/56744131?s=400&v=4"},{"name":"Chris Porter","img":"https://avatars2.githubusercontent.com/u/42626870?s=400&v=4"},{"name":"Eric Lau","img":"https://avatars0.githubusercontent.com/u/32492656?s=400&v=4"},{"name":"Evelyn Rhee","img":"https://avatars3.githubusercontent.com/u/53372490?s=400&v=4"},{"name":"Felix Huang","img":""},{"name":"Frankie Liu","img":"https://avatars2.githubusercontent.com/u/53983131?s=400&v=4"},{"name":"George Moringer","img":"https://avatars1.githubusercontent.com/u/29479653?s=400&v=4"},{"name":"Jared Rothenberg","img":"https://avatars0.githubusercontent.com/u/58494405?s=400&v=4"},{"name":"Jenny Ross Morales","img":"https://avatars0.githubusercontent.com/u/50502203?s=400&v=4"},{"name":"Karla Mazariegos","img":""},{"name":"Lee McHale","img":"https://avatars3.githubusercontent.com/u/9911007?s=400&v=4"},{"name":"Nicholas Lopez","img":""},{"name":"Paul Yi","img":"https://avatars2.githubusercontent.com/u/57200057?s=400&v=4"},{"name":"Peter Mercado","img":""},{"name":"Shu-Wei Lin","img":""},{"name":"Stacey Ng","img":"https://avatars3.githubusercontent.com/u/59713117?s=400&v=4"},{"name":"Vai San","img":"https://avatars0.githubusercontent.com/u/11686709?s=400&v=4"},{"name":"Yi Chao Chen","img":""}]